score/pyfilesystem/__init__.py
score/pyfilesystem/_init.py
score.pyfilesystem-0.0.5.dist-info/METADATA
score.pyfilesystem-0.0.5.dist-info/WHEEL
score.pyfilesystem-0.0.5.dist-info/top_level.txt
score.pyfilesystem-0.0.5.dist-info/RECORD
