Metadata-Version: 2.1
Name: score.pyfilesystem
Version: 0.0.5
Home-page: http://score-framework.org
Author: strg.at
Author-email: score@strg.at
License: LGPL
Keywords: score framework projects loader
Requires-Dist: score.init
Requires-Dist: fs
